graphscii
