Metadata-Version: 1.1
Name: graphscii
Version: 1.0.4
Summary: Print ASCII graphs in the terminal
Home-page: https://github.com/etano/graphscii
Author: Ethan W. Brown
Author-email: ethan.w.brown@gmail.com
License: MIT
Keywords: graph ascii terminal print
Platform: UNKNOWN
Classifier: Development Status :: 3 - Alpha
Classifier: Intended Audience :: Developers
Classifier: Topic :: Printing
Classifier: Topic :: Multimedia :: Graphics :: Presentation
Classifier: License :: OSI Approved :: MIT License
Classifier: Programming Language :: Python :: 2
Classifier: Programming Language :: Python :: 2.7
Classifier: Programming Language :: Python :: 3
Classifier: Programming Language :: Python :: 3.3
Classifier: Programming Language :: Python :: 3.4
Classifier: Programming Language :: Python :: 3.5
